simplejsondb/__init__.py
simplejsondb/databases.py
simplejsondb-0.4.0.dist-info/LICENSE
simplejsondb-0.4.0.dist-info/METADATA
simplejsondb-0.4.0.dist-info/WHEEL
simplejsondb-0.4.0.dist-info/top_level.txt
simplejsondb-0.4.0.dist-info/RECORD
