Metadata-Version: 2.1
Name: simplejsondb
Version: 0.4.0
Summary: Create a simple JSON database with just one line of code!
Home-page: https://github.com/RealA10N/simplejsondb
Author: RealA10N
Author-email: downtown2u@gmail.com
License: MIT
Keywords: database json csv data simple easy db
Platform: UNKNOWN
Classifier: Development Status :: 4 - Beta
Classifier: License :: OSI Approved :: MIT License
Classifier: Operating System :: OS Independent
Classifier: Topic :: Database
Classifier: Programming Language :: Python :: 3 :: Only
Classifier: Programming Language :: Python :: 3.6
Classifier: Programming Language :: Python :: 3.7
Classifier: Programming Language :: Python :: 3.8
Classifier: Programming Language :: Python :: 3.9
Requires-Python: >=3.6
License-File: LICENSE
